<?xml version = '1.0' encoding = 'UTF-8'?>
<Diagram class="oracle.dbtools.crest.swingui.relational.DPVRelational" name="Relational_1" id="BD7B392A-3891-C30A-24D0-D9FF8EA1CA44">
<createdBy>User</createdBy>
<modifiedBy>User</modifiedBy>
<createdTime>2022-12-17 17:14:43 UTC</createdTime>
<autoRoute>false</autoRoute>
<boxInbox>true</boxInbox>
<showLegend>false</showLegend>
<showLabels>false</showLabels>
<showRelAttributes>false</showRelAttributes>
<gridEnabled>false</gridEnabled>
<showGrid>false</showGrid>
<diagramColor>-1</diagramColor>
<display>false</display>
<notation>1</notation>
<objectViews>
<OView class="oracle.dbtools.crest.swingui.relational.TVTable" oid="01B16399-9BB1-C563-FC95-D1B3DC7DA911" otype="Table" vid="F11D4241-B5D7-0144-AEFD-D4C898CAA38D">
<hideElementsInCurrentOnly>false</hideElementsInCurrentOnly>
<bounds x="559" y="625" width="203" height="110"/>
</OView>
<OView class="oracle.dbtools.crest.swingui.relational.TVTable" oid="09CC299E-F673-39B8-38F7-BA7CE07E921C" otype="Table" vid="C19F0746-CB21-BD5E-D253-1A106BF78684">
<hideElementsInCurrentOnly>false</hideElementsInCurrentOnly>
<bounds x="554" y="768" width="215" height="110"/>
</OView>
<OView class="oracle.dbtools.crest.swingui.relational.TVTable" oid="1881BF9B-4BD7-57A0-1952-3A3197BED2BC" otype="Table" vid="B8425817-EB1F-6433-1E4B-20474F1E15A4">
<hideElementsInCurrentOnly>false</hideElementsInCurrentOnly>
<bounds x="115" y="17" width="202" height="217"/>
</OView>
<OView class="oracle.dbtools.crest.swingui.relational.TVTable" oid="1A369834-802B-F01B-19F5-7B60923C345A" otype="Table" vid="633E7E6A-BD29-6B75-FBE0-3AACBA9D798A">
<hideElementsInCurrentOnly>false</hideElementsInCurrentOnly>
<bounds x="292" y="699" width="170" height="134"/>
</OView>
<OView class="oracle.dbtools.crest.swingui.relational.TVTable" oid="1E0F8DAE-59EB-585D-4B69-C1392DF23511" otype="Table" vid="39BE6A4E-469F-545B-4162-5EDF9D27CBAC">
<hideElementsInCurrentOnly>false</hideElementsInCurrentOnly>
<bounds x="898" y="287" width="256" height="203"/>
</OView>
<OView class="oracle.dbtools.crest.swingui.relational.TVTable" oid="2D5D541C-BB8B-D708-9919-AFA739132F15" otype="Table" vid="567C3078-593F-99CC-B4C3-14A24F448E0D">
<hideElementsInCurrentOnly>false</hideElementsInCurrentOnly>
<bounds x="546" y="6" width="214" height="180"/>
</OView>
<OView class="oracle.dbtools.crest.swingui.relational.TVTable" oid="347E5FC7-A731-C0BF-FD18-AF1510E323CD" otype="Table" vid="18907F1C-5933-E581-A890-5FB5578F1760">
<hideElementsInCurrentOnly>false</hideElementsInCurrentOnly>
<bounds x="1271" y="282" width="229" height="205"/>
</OView>
<OView class="oracle.dbtools.crest.swingui.relational.TVTable" oid="4E3913AD-A3A0-862A-F20A-E7250816A4B3" otype="Table" vid="EA704AB4-C444-4538-1C0A-A37D34B820CC">
<hideElementsInCurrentOnly>false</hideElementsInCurrentOnly>
<bounds x="905" y="16" width="256" height="184"/>
</OView>
<OView class="oracle.dbtools.crest.swingui.relational.TVTable" oid="607D87EE-C643-94D6-9B35-7D9A85D3D1B3" otype="Table" vid="D8747932-FCAD-DBF4-F6E8-FDBF298B53A4">
<hideElementsInCurrentOnly>false</hideElementsInCurrentOnly>
<bounds x="7" y="286" width="221" height="161"/>
</OView>
<OView class="oracle.dbtools.crest.swingui.relational.TVTable" oid="69B27BA5-B632-B15F-399B-46C4A1A912C4" otype="Table" vid="0F53D41C-3C62-7F15-D44E-B695A6585638">
<hideElementsInCurrentOnly>false</hideElementsInCurrentOnly>
<bounds x="265" y="298" width="170" height="110"/>
</OView>
<OView class="oracle.dbtools.crest.swingui.relational.TVTable" oid="7920413F-EA52-C663-23F0-FA6495EF5CB0" otype="Table" vid="FEF45E51-C8BA-8F09-BC48-F3E16A6F0621">
<hideElementsInCurrentOnly>false</hideElementsInCurrentOnly>
<bounds x="510" y="241" width="302" height="313"/>
</OView>
<OView class="oracle.dbtools.crest.swingui.relational.TVTable" oid="8DF4D1A5-14D4-56E4-7DEA-30B102CFEBB0" otype="Table" vid="9DCE25C8-2FD3-BAF9-9B63-0F3E839E84E4">
<hideElementsInCurrentOnly>false</hideElementsInCurrentOnly>
<bounds x="937" y="574" width="227" height="249"/>
</OView>
<OView class="oracle.dbtools.crest.swingui.relational.TVTable" oid="BBF05BAC-DB74-6609-7551-9289A65A067F" otype="Table" vid="595FC1F4-3DAE-4ACA-3F42-7F315C812EF9">
<hideElementsInCurrentOnly>false</hideElementsInCurrentOnly>
<bounds x="54" y="504" width="170" height="127"/>
</OView>
</objectViews>
<connectors>
<Connector class="oracle.dbtools.crest.swingui.relational.TVFKRelation" oid="2A3DA13B-6949-64A4-5B51-07460CB11887" otype="FKIndexAssociation" vid_source="39BE6A4E-469F-545B-4162-5EDF9D27CBAC" vid_target="FEF45E51-C8BA-8F09-BC48-F3E16A6F0621">
<hideElementsInCurrentOnly>false</hideElementsInCurrentOnly>
<backgroundColor>-16777216</backgroundColor>
<lineWidth>1</lineWidth>
<points>
<point x="898" y="403"/>
<point x="812" y="403"/>
</points>
</Connector>
<Connector class="oracle.dbtools.crest.swingui.relational.TVFKRelation" oid="475C8F94-38F7-CF05-0234-8C1195280973" otype="FKIndexAssociation" vid_source="FEF45E51-C8BA-8F09-BC48-F3E16A6F0621" vid_target="595FC1F4-3DAE-4ACA-3F42-7F315C812EF9">
<hideElementsInCurrentOnly>false</hideElementsInCurrentOnly>
<backgroundColor>-16777216</backgroundColor>
<lineWidth>1</lineWidth>
<points>
<point x="510" y="529"/>
<point x="224" y="529"/>
</points>
</Connector>
<Connector class="oracle.dbtools.crest.swingui.relational.TVFKRelation" oid="54CEFEF1-EE94-E20A-E856-289FB0A22C19" otype="FKIndexAssociation" vid_source="39BE6A4E-469F-545B-4162-5EDF9D27CBAC" vid_target="EA704AB4-C444-4538-1C0A-A37D34B820CC">
<hideElementsInCurrentOnly>false</hideElementsInCurrentOnly>
<backgroundColor>-16777216</backgroundColor>
<lineWidth>1</lineWidth>
<points>
<point x="1029" y="287"/>
<point x="1029" y="200"/>
</points>
</Connector>
<Connector class="oracle.dbtools.crest.swingui.relational.TVFKRelation" oid="566B8371-30C9-430E-59D0-08770791E641" otype="FKIndexAssociation" vid_source="B8425817-EB1F-6433-1E4B-20474F1E15A4" vid_target="FEF45E51-C8BA-8F09-BC48-F3E16A6F0621">
<hideElementsInCurrentOnly>false</hideElementsInCurrentOnly>
<backgroundColor>-16777216</backgroundColor>
<lineWidth>1</lineWidth>
<points>
<point x="317" y="187"/>
<point x="510" y="305"/>
</points>
</Connector>
<Connector class="oracle.dbtools.crest.swingui.relational.TVFKRelation" oid="6A172B07-C6F3-3FA1-29B3-1F8FBEB9FBFC" otype="FKIndexAssociation" vid_source="39BE6A4E-469F-545B-4162-5EDF9D27CBAC" vid_target="9DCE25C8-2FD3-BAF9-9B63-0F3E839E84E4">
<hideElementsInCurrentOnly>false</hideElementsInCurrentOnly>
<backgroundColor>-16777216</backgroundColor>
<lineWidth>1</lineWidth>
<points>
<point x="1060" y="490"/>
<point x="1060" y="574"/>
</points>
</Connector>
<Connector class="oracle.dbtools.crest.swingui.relational.TVFKRelation" oid="75A343C7-B05D-DC79-56AC-6D77578339CF" otype="FKIndexAssociation" vid_source="39BE6A4E-469F-545B-4162-5EDF9D27CBAC" vid_target="18907F1C-5933-E581-A890-5FB5578F1760">
<hideElementsInCurrentOnly>false</hideElementsInCurrentOnly>
<backgroundColor>-16777216</backgroundColor>
<lineWidth>1</lineWidth>
<points>
<point x="1154" y="387"/>
<point x="1271" y="387"/>
</points>
</Connector>
<Connector class="oracle.dbtools.crest.swingui.relational.TVFKRelation" oid="7C5CB714-F5B7-65ED-32D8-F3A01E1EE210" otype="FKIndexAssociation" vid_source="567C3078-593F-99CC-B4C3-14A24F448E0D" vid_target="FEF45E51-C8BA-8F09-BC48-F3E16A6F0621">
<hideElementsInCurrentOnly>false</hideElementsInCurrentOnly>
<backgroundColor>-16777216</backgroundColor>
<lineWidth>1</lineWidth>
<points>
<point x="653" y="186"/>
<point x="653" y="241"/>
</points>
</Connector>
<Connector class="oracle.dbtools.crest.swingui.relational.TVFKRelation" oid="9A8EB15D-2F13-773C-2B1E-F9B88BC224D4" otype="FKIndexAssociation" vid_source="F11D4241-B5D7-0144-AEFD-D4C898CAA38D" vid_target="633E7E6A-BD29-6B75-FBE0-3AACBA9D798A">
<hideElementsInCurrentOnly>false</hideElementsInCurrentOnly>
<backgroundColor>-16777216</backgroundColor>
<lineWidth>1</lineWidth>
<points>
<point x="559" y="717"/>
<point x="462" y="717"/>
</points>
</Connector>
<Connector class="oracle.dbtools.crest.swingui.relational.TVFKRelation" oid="A5B27E24-A412-64AC-916D-73E9FAC1778A" otype="FKIndexAssociation" vid_source="FEF45E51-C8BA-8F09-BC48-F3E16A6F0621" vid_target="B8425817-EB1F-6433-1E4B-20474F1E15A4">
<hideElementsInCurrentOnly>false</hideElementsInCurrentOnly>
<backgroundColor>-16777216</backgroundColor>
<lineWidth>1</lineWidth>
<points>
<point x="510" y="305"/>
<point x="317" y="187"/>
</points>
</Connector>
<Connector class="oracle.dbtools.crest.swingui.relational.TVFKRelation" oid="AE4FA566-6B53-8417-C7D5-FC84C32E76E2" otype="FKIndexAssociation" vid_source="39BE6A4E-469F-545B-4162-5EDF9D27CBAC" vid_target="FEF45E51-C8BA-8F09-BC48-F3E16A6F0621">
<hideElementsInCurrentOnly>false</hideElementsInCurrentOnly>
<backgroundColor>-16777216</backgroundColor>
<lineWidth>1</lineWidth>
<points>
<point x="898" y="388"/>
<point x="812" y="388"/>
</points>
</Connector>
<Connector class="oracle.dbtools.crest.swingui.relational.TVFKRelation" oid="B28042DB-2C5B-4ACE-CC8C-8751DF38ED0F" otype="FKIndexAssociation" vid_source="9DCE25C8-2FD3-BAF9-9B63-0F3E839E84E4" vid_target="39BE6A4E-469F-545B-4162-5EDF9D27CBAC">
<hideElementsInCurrentOnly>false</hideElementsInCurrentOnly>
<backgroundColor>-16777216</backgroundColor>
<lineWidth>1</lineWidth>
<points>
<point x="1045" y="574"/>
<point x="1045" y="490"/>
</points>
</Connector>
<Connector class="oracle.dbtools.crest.swingui.relational.TVFKRelation" oid="C0648BB2-7C59-66F7-184A-D178B0A89999" otype="FKIndexAssociation" vid_source="FEF45E51-C8BA-8F09-BC48-F3E16A6F0621" vid_target="0F53D41C-3C62-7F15-D44E-B695A6585638">
<hideElementsInCurrentOnly>false</hideElementsInCurrentOnly>
<backgroundColor>-16777216</backgroundColor>
<lineWidth>1</lineWidth>
<points>
<point x="510" y="353"/>
<point x="435" y="353"/>
</points>
</Connector>
<Connector class="oracle.dbtools.crest.swingui.relational.TVFKRelation" oid="C79A14D4-1EEF-027E-A057-19498480D5DD" otype="FKIndexAssociation" vid_source="F11D4241-B5D7-0144-AEFD-D4C898CAA38D" vid_target="FEF45E51-C8BA-8F09-BC48-F3E16A6F0621">
<hideElementsInCurrentOnly>false</hideElementsInCurrentOnly>
<backgroundColor>-16777216</backgroundColor>
<lineWidth>1</lineWidth>
<points>
<point x="660" y="625"/>
<point x="660" y="554"/>
</points>
</Connector>
<Connector class="oracle.dbtools.crest.swingui.relational.TVFKRelation" oid="CB85B5FC-89E5-81E5-A0E0-F17061818F74" otype="FKIndexAssociation" vid_source="C19F0746-CB21-BD5E-D253-1A106BF78684" vid_target="633E7E6A-BD29-6B75-FBE0-3AACBA9D798A">
<hideElementsInCurrentOnly>false</hideElementsInCurrentOnly>
<backgroundColor>-16777216</backgroundColor>
<lineWidth>1</lineWidth>
<points>
<point x="554" y="800"/>
<point x="462" y="800"/>
</points>
</Connector>
<Connector class="oracle.dbtools.crest.swingui.relational.TVFKRelation" oid="D3B99D89-7F68-3BA1-8618-4E22937DE7B3" otype="FKIndexAssociation" vid_source="D8747932-FCAD-DBF4-F6E8-FDBF298B53A4" vid_target="0F53D41C-3C62-7F15-D44E-B695A6585638">
<hideElementsInCurrentOnly>false</hideElementsInCurrentOnly>
<backgroundColor>-16777216</backgroundColor>
<lineWidth>1</lineWidth>
<points>
<point x="228" y="353"/>
<point x="265" y="353"/>
</points>
</Connector>
<Connector class="oracle.dbtools.crest.swingui.relational.TVFKRelation" oid="D8C43F7C-ECE9-8A80-14CE-27EB60C24683" otype="FKIndexAssociation" vid_source="EA704AB4-C444-4538-1C0A-A37D34B820CC" vid_target="39BE6A4E-469F-545B-4162-5EDF9D27CBAC">
<hideElementsInCurrentOnly>false</hideElementsInCurrentOnly>
<backgroundColor>-16777216</backgroundColor>
<lineWidth>1</lineWidth>
<points>
<point x="1044" y="200"/>
<point x="1044" y="287"/>
</points>
</Connector>
<Connector class="oracle.dbtools.crest.swingui.relational.TVFKRelation" oid="E6602BC1-A9B5-3814-2B07-46E322679A99" otype="FKIndexAssociation" vid_source="FEF45E51-C8BA-8F09-BC48-F3E16A6F0621" vid_target="567C3078-593F-99CC-B4C3-14A24F448E0D">
<hideElementsInCurrentOnly>false</hideElementsInCurrentOnly>
<backgroundColor>-16777216</backgroundColor>
<lineWidth>1</lineWidth>
<points>
<point x="668" y="241"/>
<point x="668" y="186"/>
</points>
</Connector>
</connectors>
</Diagram>